{"SubTexture":[{"frameWidth":105,"y":281,"frameHeight":30,"height":30,"frameX":-1,"width":104,"name":"shadow","frameY":0,"x":102},{"x":203,"y":178,"width":24,"name":"arm_r_1","height":50},{"x":102,"y":311,"width":81,"name":"weapon_r","height":35},{"x":199,"y":228,"width":35,"name":"arm_r_3","height":33},{"x":161,"y":225,"width":38,"name":"arm_r_2","height":38},{"x":219,"y":367,"width":24,"name":"leg_r_1","height":27},{"x":66,"y":467,"width":17,"name":"leg_r_2","height":23},{"x":50,"y":447,"width":32,"name":"leg_r_3","height":20},{"x":227,"y":176,"width":27,"name":"leg_l_1","height":30},{"x":48,"y":467,"width":18,"name":"leg_l_2","height":24},{"x":161,"y":263,"width":32,"name":"leg_l_3","height":18},{"x":167,"y":0,"width":78,"name":"body","height":122},{"x":161,"y":178,"width":42,"name":"head_2","height":47},{"x":183,"y":311,"width":48,"name":"eye_2","height":56},{"x":167,"y":122,"width":48,"name":"head_1","height":56},{"x":50,"y":391,"width":48,"name":"eye_1","height":56},{"x":102,"y":346,"width":81,"name":"weapon_l","height":35},{"x":0,"y":460,"width":48,"name":"arm_l_1","height":48},{"x":183,"y":367,"width":36,"name":"arm_l_3","height":36},{"x":215,"y":122,"width":30,"name":"arm_l_2","height":54},{"frameWidth":185,"y":281,"frameHeight":143,"height":110,"frameX":-82,"width":102,"name":"skill1_4","frameY":-21,"x":0},{"frameWidth":185,"y":391,"frameHeight":143,"height":69,"frameX":-135,"width":50,"name":"skill1_5","frameY":-42,"x":0},{"frameWidth":185,"y":143,"frameHeight":143,"height":138,"frameX":-15,"width":161,"name":"skill1_2","frameY":-4,"x":0},{"frameWidth":185,"y":0,"frameHeight":143,"height":143,"frameX":0,"width":167,"name":"skill1_1","frameY":0,"x":0}],"imagePath":"19_butcher_tex.png","width":256,"name":"19_butcher","height":512}