{"npcId":12,"npcName":"狂战士","isChatTriggered":false,"isTradeTriggered":true,"isTransportTriggered":false,"isLearnSkillTriggered":true,"isPropertyPromotionTriggered":false,"isAddGemStoneTriggered":false,"propertyPromotionList":[{"propertyType":5,"promotion":1,"promotionPrice":100},{"propertyType":7,"promotion":1,"promotionPrice":100}],"levelDefiniteDialogGroups":[],"levelUndefiniteDialogGroups":[],"transportLevelList":[],"npcGoodsGroupList":[{"goodsList_1":[{"goodsId":401,"priceFloat":0.0,"equipmentQuality":0}],"goodsList_2":[{"goodsId":1,"priceFloat":0.0,"equipmentQuality":2}],"goodsList_3":[{"goodsId":10,"priceFloat":0.0,"equipmentQuality":1}],"goodsList_4":[{"goodsId":318,"priceFloat":0.0,"equipmentQuality":0}],"goodsList_5":[{"goodsId":211,"priceFloat":0.0,"equipmentQuality":3}]},{"goodsList_1":[{"goodsId":401,"priceFloat":0.0,"equipmentQuality":0}],"goodsList_2":[{"goodsId":20,"priceFloat":0.0,"equipmentQuality":1}],"goodsList_3":[{"goodsId":27,"priceFloat":0.0,"equipmentQuality":2}],"goodsList_4":[{"goodsId":319,"priceFloat":0.0,"equipmentQuality":0}],"goodsList_5":[{"goodsId":212,"priceFloat":0.0,"equipmentQuality":3}]},{"goodsList_1":[{"goodsId":401,"priceFloat":0.0,"equipmentQuality":0}],"goodsList_2":[{"goodsId":44,"priceFloat":0.0,"equipmentQuality":2}],"goodsList_3":[{"goodsId":53,"priceFloat":0.0,"equipmentQuality":1}],"goodsList_4":[{"goodsId":214,"priceFloat":0.0,"equipmentQuality":3}],"goodsList_5":[{"goodsId":330,"priceFloat":0.0,"equipmentQuality":0}]},{"goodsList_1":[{"goodsId":407,"priceFloat":0.0,"equipmentQuality":0}],"goodsList_2":[{"goodsId":66,"priceFloat":0.0,"equipmentQuality":2}],"goodsList_3":[{"goodsId":70,"priceFloat":0.0,"equipmentQuality":1}],"goodsList_4":[{"goodsId":312,"priceFloat":0.0,"equipmentQuality":0}],"goodsList_5":[{"goodsId":322,"priceFloat":0.0,"equipmentQuality":0}]},{"goodsList_1":[{"goodsId":407,"priceFloat":0.0,"equipmentQuality":0}],"goodsList_2":[{"goodsId":90,"priceFloat":0.0,"equipmentQuality":2}],"goodsList_3":[{"goodsId":94,"priceFloat":0.0,"equipmentQuality":1}],"goodsList_4":[{"goodsId":313,"priceFloat":0.0,"equipmentQuality":0}],"goodsList_5":[{"goodsId":323,"priceFloat":0.0,"equipmentQuality":0}]},{"goodsList_1":[{"goodsId":407,"priceFloat":0.0,"equipmentQuality":0}],"goodsList_2":[{"goodsId":222,"priceFloat":0.0,"equipmentQuality":3}],"goodsList_3":[{"goodsId":117,"priceFloat":0.0,"equipmentQuality":2}],"goodsList_4":[{"goodsId":314,"priceFloat":0.0,"equipmentQuality":0}],"goodsList_5":[{"goodsId":324,"priceFloat":0.0,"equipmentQuality":0}]},{"goodsList_1":[{"goodsId":407,"priceFloat":0.0,"equipmentQuality":0}],"goodsList_2":[{"goodsId":131,"priceFloat":0.0,"equipmentQuality":1}],"goodsList_3":[{"goodsId":135,"priceFloat":0.0,"equipmentQuality":2}],"goodsList_4":[{"goodsId":226,"priceFloat":0.0,"equipmentQuality":3}],"goodsList_5":[{"goodsId":328,"priceFloat":0.0,"equipmentQuality":0}]},{"goodsList_1":[{"goodsId":413,"priceFloat":0.0,"equipmentQuality":0}],"goodsList_2":[{"goodsId":149,"priceFloat":0.0,"equipmentQuality":1}],"goodsList_3":[{"goodsId":157,"priceFloat":0.0,"equipmentQuality":2}],"goodsList_4":[{"goodsId":340,"priceFloat":0.0,"equipmentQuality":0}],"goodsList_5":[{"goodsId":349,"priceFloat":0.0,"equipmentQuality":0}]},{"goodsList_1":[{"goodsId":413,"priceFloat":0.0,"equipmentQuality":0}],"goodsList_2":[{"goodsId":173,"priceFloat":0.0,"equipmentQuality":2}],"goodsList_3":[{"goodsId":180,"priceFloat":0.0,"equipmentQuality":2}],"goodsList_4":[{"goodsId":181,"priceFloat":0.0,"equipmentQuality":2}],"goodsList_5":[{"goodsId":350,"priceFloat":0.0,"equipmentQuality":0}]},{"goodsList_1":[{"goodsId":413,"priceFloat":0.0,"equipmentQuality":0}],"goodsList_2":[{"goodsId":182,"priceFloat":0.0,"equipmentQuality":2}],"goodsList_3":[{"goodsId":183,"priceFloat":0.0,"equipmentQuality":2}],"goodsList_4":[{"goodsId":173,"priceFloat":0.0,"equipmentQuality":2}],"goodsList_5":[{"goodsId":352,"priceFloat":0.0,"equipmentQuality":0}]}],"regularGreetings":[{"dialogId":0,"dialogContent":"拒绝挑战的人全部都是懦夫，不过你太弱小了。我不会挑战你的！","choiceIds":[]},{"dialogId":0,"dialogContent":"我对宝藏并没有什么兴趣，我来这里只是因为这里有很多人可以和我战斗。","choiceIds":[]},{"dialogId":0,"dialogContent":"我在测试自己的极限在哪里，到目前为止我已经击败2000只怪物了。","choiceIds":[]},{"dialogId":0,"dialogContent":"是时候该更换一把斧子了，原来的太轻了，不是么？","choiceIds":[]},{"dialogId":0,"dialogContent":"千万不要告诉野蛮人我在哪儿，她一直阴魂不散地跟着我，冲我傻笑。","choiceIds":[]},{"dialogId":0,"dialogContent":"据说这座城堡里有一把开山斧，具有开山裂石的威力，不知道真的假的？","choiceIds":[]}],"saveOnChange":false,"npcSkillIds":[20,30,32,38]}