{"SubTexture":[{"frameX":0,"y":1,"frameY":-1,"height":105,"frameWidth":110,"frameHeight":107,"width":109,"name":"icebg","x":1},{"frameX":0,"y":190,"frameY":-5,"height":20,"frameWidth":38,"frameHeight":25,"width":38,"name":"ice01","x":163},{"x":203,"y":161,"width":27,"name":"ice02","height":14},{"x":111,"y":160,"width":51,"name":"ice03","height":28},{"x":220,"y":51,"width":23,"name":"ice04","height":14},{"x":1,"y":108,"width":69,"name":"ice05","height":41},{"x":72,"y":108,"width":33,"name":"ice06","height":34},{"frameX":0,"y":161,"frameY":-5,"height":19,"frameWidth":38,"frameHeight":25,"width":37,"name":"w-ice01","x":164},{"frameX":0,"y":36,"frameY":0,"height":13,"frameWidth":27,"frameHeight":14,"width":26,"name":"w-ice02","x":220},{"frameX":0,"y":190,"frameY":0,"height":27,"frameWidth":51,"frameHeight":28,"width":50,"name":"w-ice03","x":111},{"frameX":0,"y":67,"frameY":0,"height":13,"frameWidth":23,"frameHeight":14,"width":22,"name":"w-ice04","x":220},{"frameX":-1,"y":151,"frameY":-1,"height":40,"frameWidth":69,"frameHeight":41,"width":68,"name":"w-ice05","x":1},{"frameX":0,"y":1,"frameY":-1,"height":33,"frameWidth":33,"frameHeight":34,"width":32,"name":"w-ice06","x":220},{"x":112,"y":1,"width":106,"name":"ringeff","height":103},{"frameX":-1,"y":106,"frameY":0,"height":52,"frameWidth":59,"frameHeight":52,"width":58,"name":"smoke01","x":112},{"frameX":0,"y":106,"frameY":0,"height":53,"frameWidth":56,"frameHeight":55,"width":56,"name":"smoke02","x":172},{"frameX":-1,"y":151,"frameY":0,"height":40,"frameWidth":38,"frameHeight":41,"width":38,"name":"smoke03","x":71}],"width":256,"name":"04_ice_effect1","imagePath":"04_ice_effect1_tex.png","height":256}